CHANGES.txt
COPYRIGHT.txt
LICENSE.txt
bootstrap.py
buildout.cfg
setup.py
src/z3c/__init__.py
src/z3c.mountpoint.egg-info/PKG-INFO
src/z3c.mountpoint.egg-info/SOURCES.txt
src/z3c.mountpoint.egg-info/dependency_links.txt
src/z3c.mountpoint.egg-info/namespace_packages.txt
src/z3c.mountpoint.egg-info/not-zip-safe
src/z3c.mountpoint.egg-info/requires.txt
src/z3c.mountpoint.egg-info/top_level.txt
src/z3c/mountpoint/README.txt
src/z3c/mountpoint/__init__.py
src/z3c/mountpoint/browser.py
src/z3c/mountpoint/browser.zcml
src/z3c/mountpoint/configure.zcml
src/z3c/mountpoint/connection.py
src/z3c/mountpoint/interfaces.py
src/z3c/mountpoint/mountpoint.py
src/z3c/mountpoint/remoteproxy.py
src/z3c/mountpoint/tests.py