Metadata-Version: 1.0
Name: z3c.mountpoint
Version: 0.1
Summary: Very simple implementation of a mount point for an object in another ZODB connection.
Home-page: http://pypi.python.org/pypi/z3c.mountpoint
Author: Stephan Richter and the Zope Community
Author-email: zope-dev@zope.org
License: ZPL 2.1
Keywords: zope3 zodb mount mountpoint
Platform: UNKNOWN
Classifier: Development Status :: 3 - Alpha
Classifier: Environment :: Web Environment
Classifier: Intended Audience :: Developers
Classifier: License :: OSI Approved :: Zope Public License
Classifier: Programming Language :: Python
Classifier: Natural Language :: English
Classifier: Operating System :: OS Independent
Classifier: Topic :: Internet :: WWW/HTTP
Classifier: Framework :: Zope3
